flask_djangoquery.py
Flask_DjangoQuery-0.2.4.dist-info/DESCRIPTION.rst
Flask_DjangoQuery-0.2.4.dist-info/METADATA
Flask_DjangoQuery-0.2.4.dist-info/metadata.json
Flask_DjangoQuery-0.2.4.dist-info/RECORD
Flask_DjangoQuery-0.2.4.dist-info/top_level.txt
Flask_DjangoQuery-0.2.4.dist-info/WHEEL
