Metadata-Version: 2.0
Name: Flask-DjangoQuery
Version: 0.2.4
Summary: Django like query for Flask-SQLAlchemy
Home-page: https://github.com/messense/Flask-DjangoQuery
Author: Messense Lv
Author-email: messense@icloud.com
License: MIT
Platform: any
Classifier: Development Status :: 4 - Beta
Classifier: Environment :: Web Environment
Classifier: Intended Audience :: Developers
Classifier: License :: OSI Approved :: MIT License
Classifier: Operating System :: OS Independent
Classifier: Programming Language :: Python
Classifier: Topic :: Internet :: WWW/HTTP :: Dynamic Content
Classifier: Topic :: Software Development :: Libraries :: Python Modules
Requires-Dist: Flask
Requires-Dist: SQLAlchemy
Requires-Dist: Flask-SQLAlchemy
